rememberme/__init__.py
rememberme/pprint.py
rememberme/rememberme.py
rememberme-0.1.0.dist-info/LICENSE
rememberme-0.1.0.dist-info/METADATA
rememberme-0.1.0.dist-info/WHEEL
rememberme-0.1.0.dist-info/top_level.txt
rememberme-0.1.0.dist-info/RECORD
