Metadata-Version: 2.1
Name: rememberme
Version: 0.1.0
Summary: Rememberme is a handy tool for memory problems in Python.
Home-page: https://github.com/liwt31/remember-me
Author: Weitang Li
Author-email: liwt31@163.com
License: MIT
Platform: UNKNOWN
Requires-Dist: print-tree2
